upload_directory/__init__.py
upload_directory/management/__init__.py
upload_directory/management/commands/__init__.py
upload_directory/management/commands/upload_to_s3.py
upload_directory-0.0.1.dist-info/DESCRIPTION.rst
upload_directory-0.0.1.dist-info/METADATA
upload_directory-0.0.1.dist-info/RECORD
upload_directory-0.0.1.dist-info/WHEEL
upload_directory-0.0.1.dist-info/metadata.json
upload_directory-0.0.1.dist-info/top_level.txt
