Metadata-Version: 2.0
Name: upload-directory
Version: 0.0.1
Summary: Django management command to upload directory to s3 bucket
Home-page: UNKNOWN
Author: Souradeep Sengupta
Author-email: souradeepsengupta95@gmail.com
License: UNKNOWN
Keywords: python,s3,directory upload
Platform: UNKNOWN
Classifier: Development Status :: 1 - Planning
Classifier: Intended Audience :: Developers
Classifier: Programming Language :: Python :: 3
Requires-Dist: boto3
Requires-Dist: django-storages
